niche_vlaanderen/__init__.py
niche_vlaanderen/acidity.py
niche_vlaanderen/cli.py
niche_vlaanderen/codetables.py
niche_vlaanderen/exception.py
niche_vlaanderen/flooding.py
niche_vlaanderen/niche.py
niche_vlaanderen/nutrient_level.py
niche_vlaanderen/spatial_context.py
niche_vlaanderen/validation.py
niche_vlaanderen/vegetation.py
niche_vlaanderen/version.py
niche_vlaanderen/system_tables/acidity.csv
niche_vlaanderen/system_tables/example.yaml
niche_vlaanderen/system_tables/hab_niche_join.csv
niche_vlaanderen/system_tables/inundation.csv
niche_vlaanderen/system_tables/lnk_acidity.csv
niche_vlaanderen/system_tables/lnk_soil_nutrient_level.csv
niche_vlaanderen/system_tables/management.csv
niche_vlaanderen/system_tables/niche_hab_rbb.csv
niche_vlaanderen/system_tables/niche_vegetation.csv
niche_vlaanderen/system_tables/nitrogen_mineralisation.csv
niche_vlaanderen/system_tables/nutrient_level.csv
niche_vlaanderen/system_tables/seepage.csv
niche_vlaanderen/system_tables/soil_codes.csv
niche_vlaanderen/system_tables/soil_mlw_class.csv
niche_vlaanderen/system_tables/vegetatietypen.csv
niche_vlaanderen/system_tables/vegetatietypen_DeNocker.csv
niche_vlaanderen/system_tables/flooding/depth.csv
niche_vlaanderen/system_tables/flooding/duration.csv
niche_vlaanderen/system_tables/flooding/frequency.csv
niche_vlaanderen/system_tables/flooding/lnk_potential.csv
niche_vlaanderen/system_tables/flooding/potential.csv
niche_vlaanderen-2.1.dist-info/AUTHORS.rst
niche_vlaanderen-2.1.dist-info/LICENSE
niche_vlaanderen-2.1.dist-info/METADATA
niche_vlaanderen-2.1.dist-info/WHEEL
niche_vlaanderen-2.1.dist-info/entry_points.txt
niche_vlaanderen-2.1.dist-info/top_level.txt
niche_vlaanderen-2.1.dist-info/RECORD
