Metadata-Version: 2.1
Name: niche-vlaanderen
Version: 2.1
Summary: NICHE Vlaanderen: hydro-ecological model for valley-ecosystems in Flanders
Home-page: https://github.com/inbo/niche_vlaanderen
Author: Johan Van de Wauw
Author-email: johan.vandewauw@inbo.be
License: MIT
Platform: UNKNOWN
Classifier: Development Status :: 5 - Production/Stable
Classifier: Intended Audience :: Science/Research
Classifier: License :: OSI Approved :: MIT License
Classifier: Programming Language :: Python :: 3.9
Classifier: Programming Language :: Python :: 3.10
Classifier: Programming Language :: Python :: 3.11
License-File: LICENSE
License-File: AUTHORS.rst
Requires-Dist: geopandas
Requires-Dist: matplotlib
Requires-Dist: numpy
Requires-Dist: pandas
Requires-Dist: pygeos
Requires-Dist: pyyaml
Requires-Dist: rasterio
Requires-Dist: rasterstats (>=0.17)
Requires-Dist: tqdm
